musamusa_etr/aboutproject.py
musamusa_etr/etr.py
musamusa_etr/etr_line.py
musamusa_etr/utils.py
musamusa_etr-0.1.6.dist-info/LICENSE
musamusa_etr-0.1.6.dist-info/WHEEL
musamusa_etr-0.1.6.dist-info/METADATA
musamusa_etr-0.1.6.dist-info/RECORD
