Metadata-Version: 2.1
Name: musamusa-etr
Version: 0.1.6
Summary: Easy To Read text format file
License: GPLv3
Author: suizokukan
Author-email: suizokukan@orange.fr
Requires-Python: >=3.9,<4.0
Classifier: License :: Other/Proprietary License
Classifier: Programming Language :: Python :: 3
Classifier: Programming Language :: Python :: 3.9
Requires-Dist: musamusa-errors (>=0.8,<0.9)
Requires-Dist: musamusa-fal (>=0.0.4,<0.0.5)
